cjnfuncs/SMTP.py
cjnfuncs/__init__.py
cjnfuncs/configman.py
cjnfuncs/core.py
cjnfuncs/deployfiles.py
cjnfuncs/mungePath.py
cjnfuncs/resourcelock.py
cjnfuncs/rwt.py
cjnfuncs/timevalue.py
cjnfuncs-3.1.dist-info/licenses/LICENSE
cjnfuncs-3.1.dist-info/METADATA
cjnfuncs-3.1.dist-info/WHEEL
cjnfuncs-3.1.dist-info/entry_points.txt
cjnfuncs-3.1.dist-info/top_level.txt
cjnfuncs-3.1.dist-info/RECORD
