Metadata-Version: 2.4
Name: cjnfuncs
Version: 3.1
Summary: A collection of core functions for tool script writing
Author-email: Chris Nelson <github@cjnaz.com>
License-Expression: MIT
Project-URL: repository, https://github.com/cjnaz/cjnfuncs
Keywords: cjnaz,library,cjnfuncs
Classifier: Programming Language :: Python :: 3
Classifier: Topic :: Software Development :: Libraries :: Python Modules
Requires-Python: >=3.9
License-File: LICENSE
Requires-Dist: requests
Requires-Dist: appdirs>=1.4
Requires-Dist: dkimpy
Requires-Dist: importlib_resources
Requires-Dist: posix-ipc>=1.1.1; sys_platform == "linux"
Dynamic: license-file
